poetry_org/__init__.py
poetry_org/poetry_org.py
poetry_org-0.1.8.dist-info/entry_points.txt
poetry_org-0.1.8.dist-info/LICENSE
poetry_org-0.1.8.dist-info/WHEEL
poetry_org-0.1.8.dist-info/METADATA
poetry_org-0.1.8.dist-info/RECORD
